maple_mcp_server1_0/__init__.py
maple_mcp_server1_0-0.1.0.dist-info/WHEEL
maple_mcp_server1_0-0.1.0.dist-info/entry_points.txt
maple_mcp_server1_0-0.1.0.dist-info/METADATA
maple_mcp_server1_0-0.1.0.dist-info/RECORD
