Metadata-Version: 2.3
Name: maple-mcp-server1-0
Version: 0.1.0
Summary: Add your description here
Author: leaves
Author-email: leaves <106875596+airleaves@users.noreply.github.com>
Requires-Dist: mcp[cli]>=1.12.2
Requires-Python: >=3.13
